{
  "lastChecks": {
    "gateway": "2026-03-22T09:36:00Z",
    "memory_optimizer": "2026-03-22T09:36:00Z",
    "agent_qscores": "2026-03-21T20:57:00Z",
    "memory_maintenance": "2026-03-21T19:20:00Z",
    "projects_tasks": "2026-03-21T20:00:00Z",
    "syncs_infrastructure": "2026-03-22T04:04:00Z",
    "research_knowledge": "2026-02-01T14:00:00Z"
  },
  "last_updated": "2026-03-22T09:36:00Z",
  "current_checks": [
    "memory_optimizer (just ran 2026-03-22 04:06)",
    "syncs_infrastructure (just ran 2026-03-22 04:04)",
    "phase7b_insights (just ran 2026-03-22 04:02)"
  ]
}
